[
 {
   "dataName": "MartianSpecialMine",
   "friendlyName": "Martian Special",
   "modifyBySize": false,
   "descriptor": "",
   "modelValue": null,
   "water_mean": 0,
   "water_width": ,
   "water_min": 0,
   "water_jump": 0,
   "volatiles_mean": 0,
   "volatiles_width": 0,
   "volatiles_min": 0,
   "volatiles_jump": 0,
   "metals_mean": 15,
   "metals_width": 5,
   "metals_min": 5,
   "metals_jump": 0.2,
   "nobles_mean": 0,
   "nobles_width": 0,
   "nobles_min": 0,
   "nobles_jump": 00,
   "fissiles_mean": 1,
   "fissiles_width": 3,
   "fissiles_min": 0,
   "fissiles_jump": 0.7,
   "Notes": ""
 }
]